PlusMath/__init__.py
PlusMath/__main__.py
PlusMath/MoreFunctions/ArithmaticEquations.py
PlusMath/MoreFunctions/__init__.py
PlusMath/MoreTypes/Functions.py
PlusMath/MoreTypes/Numbers.py
PlusMath/MoreTypes/__init__.py
PlusMath/MoreTypes/MoreExceptions/DivisionErrors.py
PlusMath/MoreTypes/MoreExceptions/__init__.py
PlusMath/Vectors/ThreeDimensions.py
PlusMath/Vectors/TwoDimensions.py
PlusMath/Vectors/__init__.py
PlusMath-1.0.4.1.dist-info/METADATA
PlusMath-1.0.4.1.dist-info/WHEEL
PlusMath-1.0.4.1.dist-info/license.txt
PlusMath-1.0.4.1.dist-info/top_level.txt
PlusMath-1.0.4.1.dist-info/RECORD
