Metadata-Version: 2.1
Name: PlusMath
Version: 1.0.4.1
Summary: Does Python not have enough math tools? PlusMath is here to help!
Home-page: https://github.com/cornusandu/MoreMath
Author: Sandu Bogdan
Author-email: bogdanelsandu@hotmail.com
Project-URL: Bug Tracker, https://github.com/cornusandu/MoreMath/issues
Project-URL: GitHub Repository, https://github.com/cornusandu/MoreMath
Classifier: Programming Language :: Python :: 3
Classifier: License :: OSI Approved :: MIT License
Classifier: Operating System :: OS Independent
Requires-Python: >=3.10
License-File: license.txt
